adn/__init__.py
adn/adn.py
adn/example.py
adn/attentions/__init__.py
adn/attentions/consts.py
adn/attentions/efficient.py
adn/attentions/favorplus.py
adn/attentions/full.py
adn/attentions/group.py
adn/attentions/linear.py
adn/attentions/linformer.py
adn/attentions/lsh.py
adn_torch-0.0.2.dist-info/LICENSE
adn_torch-0.0.2.dist-info/METADATA
adn_torch-0.0.2.dist-info/WHEEL
adn_torch-0.0.2.dist-info/top_level.txt
adn_torch-0.0.2.dist-info/RECORD
