Metadata-Version: 2.1
Name: adn-torch
Version: 0.0.2
Summary: Attention Diffusion Network implementation in Pytorch
Home-page: https://github.com/radandreicristian/adn
Author: Andrei-Cristian Rad
Author-email: radandreicristian@gmail.com
License: MIT
Keywords: attention,artificial intelligence,deep learning,traffic
Classifier: Development Status :: 4 - Beta
Classifier: Intended Audience :: Developers
Classifier: Topic :: Scientific/Engineering :: Artificial Intelligence
Classifier: License :: OSI Approved :: MIT License
Classifier: Programming Language :: Python :: 3.9
License-File: LICENSE
Requires-Dist: torch
